simplelog/__init__.py
simplelog/config.py
simplelog/const.py
simplelog/log.py
python_simple_log-1.0.0.dist-info/LICENSE.md
python_simple_log-1.0.0.dist-info/METADATA
python_simple_log-1.0.0.dist-info/WHEEL
python_simple_log-1.0.0.dist-info/top_level.txt
python_simple_log-1.0.0.dist-info/RECORD
